metkitlib/__init__.py
metkitlib/bin/bufr-sanity-check
metkitlib/bin/compare-mars-requests.py
metkitlib/bin/mars-archive-script
metkitlib/bin/parse-mars-request
metkitlib/include/metkit/metkit_config.h
metkitlib/include/metkit/metkit_ecbuild_config.h
metkitlib/include/metkit/metkit_version.h
metkitlib/include/metkit/api/metkit_c.h
metkitlib/include/metkit/codes/BUFRDecoder.h
metkitlib/include/metkit/codes/BufrContent.h
metkitlib/include/metkit/codes/CodesContent.h
metkitlib/include/metkit/codes/CodesHandleDeleter.h
metkitlib/include/metkit/codes/CodesSplitter.h
metkitlib/include/metkit/codes/GRIBDecoder.h
metkitlib/include/metkit/codes/GribAccessor.h
metkitlib/include/metkit/codes/GribHandle.h
metkitlib/include/metkit/codes/GribIterator.h
metkitlib/include/metkit/codes/LibEccodes.h
metkitlib/include/metkit/codes/MallocCodesContent.h
metkitlib/include/metkit/codes/api/CodesAPI.h
metkitlib/include/metkit/codes/api/CodesTypes.h
metkitlib/include/metkit/codes/api/GeoIterator.h
metkitlib/include/metkit/codes/api/KeyIterator.h
metkitlib/include/metkit/config/LibMetkit.h
metkitlib/include/metkit/fields/FieldIndex.h
metkitlib/include/metkit/fields/FieldIndexList.h
metkitlib/include/metkit/fields/SimpleFieldIndex.h
metkitlib/include/metkit/hypercube/HyperCube.h
metkitlib/include/metkit/hypercube/HyperCubePayloaded.h
metkitlib/include/metkit/mars/BaseProtocol.h
metkitlib/include/metkit/mars/ClientTask.h
metkitlib/include/metkit/mars/DHSProtocol.h
metkitlib/include/metkit/mars/MarsExpandContext.h
metkitlib/include/metkit/mars/MarsExpansion.h
metkitlib/include/metkit/mars/MarsExpension.h
metkitlib/include/metkit/mars/MarsHandle.h
metkitlib/include/metkit/mars/MarsLanguage.h
metkitlib/include/metkit/mars/MarsLocation.h
metkitlib/include/metkit/mars/MarsParsedRequest.h
metkitlib/include/metkit/mars/MarsParser.h
metkitlib/include/metkit/mars/MarsRequest.h
metkitlib/include/metkit/mars/MarsRequestHandle.h
metkitlib/include/metkit/mars/Matcher.h
metkitlib/include/metkit/mars/Param.b
metkitlib-1.16.0.9.dist-info/licenses/AUTHORS
metkitlib-1.16.0.9.dist-info/licenses/LICENSE
metkitlib-1.16.0.9.dist-info/METADATA
metkitlib-1.16.0.9.dist-info/WHEEL
metkitlib-1.16.0.9.dist-info/top_level.txt
metkitlib-1.16.0.9.dist-info/RECORD
